speaker_detector/__main__.py
speaker_detector/cli.py
speaker_detector/constants.py
speaker_detector/core.py
speaker_detector/server copy.py
speaker_detector/server.py
speaker_detector/speaker_state.py
speaker_detector/model/ECAPA_TDNN.py
speaker_detector/model/classifier.ckpt
speaker_detector/model/embedding_model.ckpt
speaker_detector/model/hyperparams.yaml
speaker_detector/model/label_encoder.ckpt
speaker_detector/model/mean_var_norm_emb.ckpt
speaker_detector/routes/background_loop.py
speaker_detector/routes/background_routes.py
speaker_detector/routes/correction_routes.py
speaker_detector/routes/events_routes.py
speaker_detector/routes/identify_routes.py
speaker_detector/routes/index_routes.py
speaker_detector/routes/listening_mode_routes copy.py
speaker_detector/routes/listening_mode_routes.py
speaker_detector/routes/logs_routes.py
speaker_detector/routes/meetings_routes.py
speaker_detector/routes/rebuild_routes.py
speaker_detector/routes/recordings_routes.py
speaker_detector/routes/speaker_routes.py
speaker_detector/routes/version_routes.py
speaker_detector/utils/__init__.py
speaker_detector/utils/analyze.py
speaker_detector/utils/audio.py
speaker_detector/utils/combine.py
speaker_detector/utils/export_embeddings.py
speaker_detector/utils/export_model.py
speaker_detector/utils/generate_summary.py
speaker_detector/utils/paths.py
speaker_detector/web/static/__init__.py
speaker_detector/web/static/favicon.ico
speaker_detector/web/static/index copy.html
speaker_detector/web/static/index.html
speaker_detector/web/static/style.css
speaker_detector/web/static/components/accordion-nav/accordion-nav.css
speaker_detector/web/static/components/accordion-nav/accordion-nav.html
speaker_detector/web/static/components/accordion-nav/accordion-nav.js
speaker_detector/web/static/components/correction/correction.css
speaker_detector/web/static/components/correction/correction.html
speaker_detector/web/static/components/correction/correction.js
speaker_detector-0.2.4.dist-info/METADATA
speaker_detector-0.2.4.dist-info/WHEEL
speaker_detector-0.2.4.dist-info/entry_points.txt
speaker_detector-0.2.4.dist-info/top_level.txt
speaker_detector-0.2.4.dist-info/RECORD
